{
	"info": {
		"_postman_id": "f6d28a3d-78c1-4404-864b-066cce0fd00f",
		"name": "Nba",
		"schema": "https://schema.getpostman.com/json/collection/v2.1.0/collection.json"
	},
	"item": [
		{
			"name": "Public End Points",
			"item": [
				{
					"name": "Get Venues",
					"event": [
						{
							"listen": "test",
							"script": {
								"exec": [
									"pm.test('Status code OK', function(){\r",
									"    pm.response.to.have.status(200)\r",
									"})\r",
									"\r",
									"pm.test('return array', function(){\r",
									"    var jsonData = pm.response.json()\r",
									"    pm.expect(jsonData.venues).to.be.an('array')\r",
									"})"
								],
								"type": "text/javascript"
							}
						}
					],
					"protocolProfileBehavior": {
						"disableBodyPruning": true
					},
					"request": {
						"method": "GET",
						"header": [],
						"body": {
							"mode": "raw",
							"raw": "",
							"options": {
								"raw": {
									"language": "json"
								}
							}
						},
						"url": {
							"raw": "https://udacity-nba-api.herokuapp.com/venues",
							"protocol": "https",
							"host": [
								"udacity-nba-api",
								"herokuapp",
								"com"
							],
							"path": [
								"venues"
							]
						},
						"description": "Updates a venue "
					},
					"response": []
				},
				{
					"name": "Get Players",
					"event": [
						{
							"listen": "test",
							"script": {
								"exec": [
									"pm.test('Status code OK', function(){\r",
									"    pm.response.to.have.status(200)\r",
									"})\r",
									"\r",
									"pm.test('return array', function(){\r",
									"    var jsonData = pm.response.json()\r",
									"    pm.expect(jsonData.players).to.be.an('array')\r",
									"})"
								],
								"type": "text/javascript"
							}
						}
					],
					"protocolProfileBehavior": {
						"disableBodyPruning": true
					},
					"request": {
						"method": "GET",
						"header": [],
						"body": {
							"mode": "raw",
							"raw": "",
							"options": {
								"raw": {
									"language": "json"
								}
							}
						},
						"url": {
							"raw": "https://udacity-nba-api.herokuapp.com/players",
							"protocol": "https",
							"host": [
								"udacity-nba-api",
								"herokuapp",
								"com"
							],
							"path": [
								"players"
							]
						},
						"description": "Get players in the database "
					},
					"response": []
				},
				{
					"name": "Get Teams",
					"event": [
						{
							"listen": "test",
							"script": {
								"exec": [
									"pm.test('Status code OK', function(){\r",
									"    pm.response.to.have.status(200)\r",
									"})\r",
									"\r",
									"pm.test('return array', function(){\r",
									"    var jsonData = pm.response.json()\r",
									"    pm.expect(jsonData.teams).to.be.an('array')\r",
									"})"
								],
								"type": "text/javascript"
							}
						}
					],
					"protocolProfileBehavior": {
						"disableBodyPruning": true
					},
					"request": {
						"method": "GET",
						"header": [],
						"body": {
							"mode": "raw",
							"raw": "",
							"options": {
								"raw": {
									"language": "json"
								}
							}
						},
						"url": {
							"raw": "https://udacity-nba-api.herokuapp.com/teams",
							"protocol": "https",
							"host": [
								"udacity-nba-api",
								"herokuapp",
								"com"
							],
							"path": [
								"teams"
							]
						},
						"description": "Get teams in the api "
					},
					"response": []
				},
				{
					"name": "Get Events",
					"event": [
						{
							"listen": "test",
							"script": {
								"exec": [
									"pm.test('Status code OK', function(){\r",
									"    pm.response.to.have.status(200)\r",
									"})\r",
									"\r",
									"pm.test('return array', function(){\r",
									"    var jsonData = pm.response.json()\r",
									"    pm.expect(jsonData.events).to.be.an('array')\r",
									"})"
								],
								"type": "text/javascript"
							}
						}
					],
					"protocolProfileBehavior": {
						"disableBodyPruning": true
					},
					"request": {
						"method": "GET",
						"header": [],
						"body": {
							"mode": "raw",
							"raw": "",
							"options": {
								"raw": {
									"language": "json"
								}
							}
						},
						"url": {
							"raw": "https://udacity-nba-api.herokuapp.com/events",
							"protocol": "https",
							"host": [
								"udacity-nba-api",
								"herokuapp",
								"com"
							],
							"path": [
								"events"
							]
						},
						"description": "Get events in the api"
					},
					"response": []
				},
				{
					"name": "Get Venues - By Search Term",
					"event": [
						{
							"listen": "test",
							"script": {
								"exec": [
									"pm.test('Status code OK', function(){\r",
									"    pm.response.to.have.status(200)\r",
									"})\r",
									"\r",
									"pm.test('return array', function(){\r",
									"    var jsonData = pm.response.json()\r",
									"    pm.expect(jsonData.venues).to.be.an('array')\r",
									"})"
								],
								"type": "text/javascript"
							}
						}
					],
					"request": {
						"method": "GET",
						"header": [],
						"url": {
							"raw": "https://udacity-nba-api.herokuapp.com/venues?search_term=a",
							"protocol": "https",
							"host": [
								"udacity-nba-api",
								"herokuapp",
								"com"
							],
							"path": [
								"venues"
							],
							"query": [
								{
									"key": "search_term",
									"value": "a"
								}
							]
						},
						"description": "Get venues by search term "
					},
					"response": []
				},
				{
					"name": "Get Players - By Search Term",
					"event": [
						{
							"listen": "test",
							"script": {
								"exec": [
									"pm.test('Status code OK', function(){\r",
									"    pm.response.to.have.status(200)\r",
									"})\r",
									"\r",
									"pm.test('return array', function(){\r",
									"    var jsonData = pm.response.json()\r",
									"    pm.expect(jsonData.players).to.be.an('array')\r",
									"})"
								],
								"type": "text/javascript"
							}
						}
					],
					"request": {
						"method": "GET",
						"header": [],
						"url": {
							"raw": "https://udacity-nba-api.herokuapp.com/players?search_term=curry",
							"protocol": "https",
							"host": [
								"udacity-nba-api",
								"herokuapp",
								"com"
							],
							"path": [
								"players"
							],
							"query": [
								{
									"key": "search_term",
									"value": "curry"
								}
							]
						},
						"description": "Get player by name or last name"
					},
					"response": []
				},
				{
					"name": "Get Teams - By Search Term",
					"event": [
						{
							"listen": "test",
							"script": {
								"exec": [
									"pm.test('Status code OK', function(){\r",
									"    pm.response.to.have.status(200)\r",
									"})\r",
									"\r",
									"pm.test('return array', function(){\r",
									"    var jsonData = pm.response.json()\r",
									"    pm.expect(jsonData.teams).to.be.an('array')\r",
									"})"
								],
								"type": "text/javascript"
							}
						}
					],
					"request": {
						"method": "GET",
						"header": [],
						"url": {
							"raw": "https://udacity-nba-api.herokuapp.com/teams?search_term=ce",
							"protocol": "https",
							"host": [
								"udacity-nba-api",
								"herokuapp",
								"com"
							],
							"path": [
								"teams"
							],
							"query": [
								{
									"key": "search_term",
									"value": "ce"
								}
							]
						},
						"description": "get teams by the search term = name "
					},
					"response": []
				},
				{
					"name": "Post Venue",
					"event": [
						{
							"listen": "test",
							"script": {
								"exec": [
									"pm.test('Status code 401', function(){\r",
									"    pm.response.to.have.status(401)\r",
									"})\r",
									"\r",
									""
								],
								"type": "text/javascript"
							}
						}
					],
					"request": {
						"method": "POST",
						"header": [],
						"url": {
							"raw": "https://udacity-nba-api.herokuapp.com/venues",
							"protocol": "https",
							"host": [
								"udacity-nba-api",
								"herokuapp",
								"com"
							],
							"path": [
								"venues"
							]
						},
						"description": "try to put from public account - expects 401 unathorize response "
					},
					"response": []
				},
				{
					"name": "Post Players",
					"event": [
						{
							"listen": "test",
							"script": {
								"exec": [
									"pm.test('Status code 401', function(){\r",
									"    pm.response.to.have.status(401)\r",
									"})\r",
									"\r",
									""
								],
								"type": "text/javascript"
							}
						}
					],
					"request": {
						"method": "POST",
						"header": [],
						"url": {
							"raw": "https://udacity-nba-api.herokuapp.com/players",
							"protocol": "https",
							"host": [
								"udacity-nba-api",
								"herokuapp",
								"com"
							],
							"path": [
								"players"
							]
						},
						"description": "Try to post players from public account "
					},
					"response": []
				},
				{
					"name": "Post Team",
					"event": [
						{
							"listen": "test",
							"script": {
								"exec": [
									"pm.test('Status code 401', function(){\r",
									"    pm.response.to.have.status(401)\r",
									"})\r",
									"\r",
									""
								],
								"type": "text/javascript"
							}
						}
					],
					"request": {
						"method": "POST",
						"header": [],
						"url": {
							"raw": "https://udacity-nba-api.herokuapp.com/teams",
							"protocol": "https",
							"host": [
								"udacity-nba-api",
								"herokuapp",
								"com"
							],
							"path": [
								"teams"
							]
						},
						"description": "try to post a team from unauthorize account"
					},
					"response": []
				},
				{
					"name": "Post Events",
					"event": [
						{
							"listen": "test",
							"script": {
								"exec": [
									"pm.test('Status code 401', function(){\r",
									"    pm.response.to.have.status(401)\r",
									"})\r",
									"\r",
									""
								],
								"type": "text/javascript"
							}
						}
					],
					"request": {
						"method": "POST",
						"header": [],
						"url": {
							"raw": "https://udacity-nba-api.herokuapp.com/events",
							"protocol": "https",
							"host": [
								"udacity-nba-api",
								"herokuapp",
								"com"
							],
							"path": [
								"events"
							]
						},
						"description": "try to post a events from unauthorized account"
					},
					"response": []
				},
				{
					"name": "Patch Venue",
					"event": [
						{
							"listen": "test",
							"script": {
								"exec": [
									"pm.test('Status code 401', function(){\r",
									"    pm.response.to.have.status(401)\r",
									"})\r",
									"\r",
									""
								],
								"type": "text/javascript"
							}
						}
					],
					"request": {
						"method": "PATCH",
						"header": [],
						"url": {
							"raw": "https://udacity-nba-api.herokuapp.com/venues/2",
							"protocol": "https",
							"host": [
								"udacity-nba-api",
								"herokuapp",
								"com"
							],
							"path": [
								"venues",
								"2"
							]
						},
						"description": "try to patch acount from unauthorize account"
					},
					"response": []
				},
				{
					"name": "Patch players",
					"event": [
						{
							"listen": "test",
							"script": {
								"exec": [
									"pm.test('Status code 401', function(){\r",
									"    pm.response.to.have.status(401)\r",
									"})\r",
									"\r",
									""
								],
								"type": "text/javascript"
							}
						}
					],
					"request": {
						"method": "PATCH",
						"header": [],
						"url": {
							"raw": "https://udacity-nba-api.herokuapp.com/players/2",
							"protocol": "https",
							"host": [
								"udacity-nba-api",
								"herokuapp",
								"com"
							],
							"path": [
								"players",
								"2"
							]
						},
						"description": "try to patch players from unauthorize account "
					},
					"response": []
				},
				{
					"name": "Patch teams",
					"event": [
						{
							"listen": "test",
							"script": {
								"exec": [
									"pm.test('Status code 401', function(){\r",
									"    pm.response.to.have.status(401)\r",
									"})\r",
									"\r",
									""
								],
								"type": "text/javascript"
							}
						}
					],
					"request": {
						"method": "PATCH",
						"header": [],
						"url": {
							"raw": "https://udacity-nba-api.herokuapp.com/teams/2",
							"protocol": "https",
							"host": [
								"udacity-nba-api",
								"herokuapp",
								"com"
							],
							"path": [
								"teams",
								"2"
							]
						},
						"description": "try to patch teams from unauthorize account"
					},
					"response": []
				},
				{
					"name": "Path Events ",
					"event": [
						{
							"listen": "test",
							"script": {
								"exec": [
									"pm.test('Status code 401', function(){\r",
									"    pm.response.to.have.status(401)\r",
									"})\r",
									"\r",
									""
								],
								"type": "text/javascript"
							}
						}
					],
					"request": {
						"method": "PATCH",
						"header": [],
						"url": {
							"raw": "https://udacity-nba-api.herokuapp.com/events/2",
							"protocol": "https",
							"host": [
								"udacity-nba-api",
								"herokuapp",
								"com"
							],
							"path": [
								"events",
								"2"
							]
						},
						"description": "try to patch events from public account"
					},
					"response": []
				},
				{
					"name": "Delete Players",
					"event": [
						{
							"listen": "test",
							"script": {
								"exec": [
									"pm.test('Status code 401', function(){\r",
									"    pm.response.to.have.status(401)\r",
									"})\r",
									"\r",
									""
								],
								"type": "text/javascript"
							}
						}
					],
					"request": {
						"method": "DELETE",
						"header": [],
						"url": {
							"raw": "https://udacity-nba-api.herokuapp.com/players/2",
							"protocol": "https",
							"host": [
								"udacity-nba-api",
								"herokuapp",
								"com"
							],
							"path": [
								"players",
								"2"
							]
						},
						"description": "try to delete players using public account"
					},
					"response": []
				},
				{
					"name": "Delete Events ",
					"event": [
						{
							"listen": "test",
							"script": {
								"exec": [
									"pm.test('Status code 401', function(){\r",
									"    pm.response.to.have.status(401)\r",
									"})\r",
									"\r",
									""
								],
								"type": "text/javascript"
							}
						}
					],
					"request": {
						"method": "DELETE",
						"header": [],
						"url": {
							"raw": "https://udacity-nba-api.herokuapp.com/venues/2",
							"protocol": "https",
							"host": [
								"udacity-nba-api",
								"herokuapp",
								"com"
							],
							"path": [
								"venues",
								"2"
							]
						},
						"description": "try to delete event in public account "
					},
					"response": []
				},
				{
					"name": "Delete Teams",
					"event": [
						{
							"listen": "test",
							"script": {
								"exec": [
									"pm.test('Status code 401', function(){\r",
									"    pm.response.to.have.status(401)\r",
									"})\r",
									"\r",
									""
								],
								"type": "text/javascript"
							}
						}
					],
					"request": {
						"method": "DELETE",
						"header": [],
						"url": {
							"raw": "https://udacity-nba-api.herokuapp.com/events/1",
							"protocol": "https",
							"host": [
								"udacity-nba-api",
								"herokuapp",
								"com"
							],
							"path": [
								"events",
								"1"
							]
						},
						"description": "try to delete a team using public account "
					},
					"response": []
				}
			]
		},
		{
			"name": "Team Manager",
			"item": [
				{
					"name": "Post Player",
					"event": [
						{
							"listen": "test",
							"script": {
								"exec": [
									"pm.test('Status code 200', function(){\r",
									"    pm.response.to.have.status(200)\r",
									"})"
								],
								"type": "text/javascript"
							}
						}
					],
					"request": {
						"auth": {
							"type": "bearer",
							"bearer": [
								{
									"key": "token",
									"value": "eyJhbGciOiJSUzI1NiIsInR5cCI6IkpXVCIsImtpZCI6Im5YcFc4ZWRMbmR6aFFQOUZjTXNyOSJ9.eyJpc3MiOiJodHRwczovL2F1dGgwLWZzbmQudXMuYXV0aDAuY29tLyIsInN1YiI6ImF1dGgwfDVmZmRkZTQ4MTMwOWUzMDA2OWM0MzRiNCIsImF1ZCI6Im5iYV9kYXRhX2FwaSIsImlhdCI6MTYxNDcwNjMyOSwiZXhwIjoxNjE0NzEzNTI5LCJhenAiOiJmM0RLcWpxOEsySGhKZnI5dWJOU25ReFY2YVl4MjJaWiIsInNjb3BlIjoiIiwicGVybWlzc2lvbnMiOlsiZGVsZXRlOnBsYXllcnMiLCJwYXRjaDpwbGF5ZXJzIiwicGF0Y2g6dGVhbXMiLCJwb3N0OnBsYXllcnMiXX0.pJPc92DSjvrOjRKDQ5j7oGpBd-4aiBlQZgpk78agD3pq96unZyNdmYYA7eG9DoV1WZ5sS_5mrEei1NBBzZItKRIMURS9qHWnr2nqAfsQzamMAnKL9MZzYHQ3Uq2lYqSl3hjejZaxOdt7wnGbzxwPbiszkQ51PkJ8LzC2UOLFu684hNxjXyXCV1XOCc8jcwcVUlohQVzcTt_wqCjw7HZ_B9yfrVnYruoNnTKMkjzKGjGg10GbA4FEft7y1PDdyZH4OEpSuLdzJqkYTYToD2TbnBTpTEaeyObND1eN29x3AhBhfjzDljcG-Qdk-3TSa2hMUc-NPRY4rMKNI4XgAU9JUg",
									"type": "string"
								}
							]
						},
						"method": "POST",
						"header": [],
						"body": {
							"mode": "raw",
							"raw": "{\n\t\"first_name\": \"Gordon\",\n\t\"last_name\": \"Hayward\",\n    \"player_number\": 20,\n\t\"team\": \"Hornets\",\n\t\"mpg\": 24.6,\n\t\"ppg\": 12.5,\n\t\"rpg\": 2.6,\n\t\"apg\": 4.9,\n\t\"team_id\": 11\n}",
							"options": {
								"raw": {
									"language": "json"
								}
							}
						},
						"url": {
							"raw": "https://udacity-nba-api.herokuapp.com/players",
							"protocol": "https",
							"host": [
								"udacity-nba-api",
								"herokuapp",
								"com"
							],
							"path": [
								"players"
							]
						},
						"description": "post a player to api "
					},
					"response": []
				},
				{
					"name": "Updated Team",
					"event": [
						{
							"listen": "test",
							"script": {
								"exec": [
									"pm.test('Status code 200', function(){\r",
									"    pm.response.to.have.status(200)\r",
									"})"
								],
								"type": "text/javascript"
							}
						}
					],
					"request": {
						"auth": {
							"type": "bearer",
							"bearer": [
								{
									"key": "token",
									"value": "eyJhbGciOiJSUzI1NiIsInR5cCI6IkpXVCIsImtpZCI6Im5YcFc4ZWRMbmR6aFFQOUZjTXNyOSJ9.eyJpc3MiOiJodHRwczovL2F1dGgwLWZzbmQudXMuYXV0aDAuY29tLyIsInN1YiI6ImF1dGgwfDVmZmRkZTQ4MTMwOWUzMDA2OWM0MzRiNCIsImF1ZCI6Im5iYV9kYXRhX2FwaSIsImlhdCI6MTYxNDMxNjQ3MCwiZXhwIjoxNjE0MzIzNjcwLCJhenAiOiJmM0RLcWpxOEsySGhKZnI5dWJOU25ReFY2YVl4MjJaWiIsInNjb3BlIjoiIiwicGVybWlzc2lvbnMiOlsiZGVsZXRlOnBsYXllcnMiLCJwYXRjaDpwbGF5ZXJzIiwicGF0Y2g6dGVhbXMiLCJwb3N0OnBsYXllcnMiXX0.KA4eopbhlFtFLuK9G8NfKFuAQkE-rEeg21NyG0Jb3Ht1fKIzSltqPvyjLZKglhWf4i1woMMZI6EeqAijuMSYO6dnxa_UBRKmTEsPHOoFCNPPW-uaRqco1l0bHZKeNExQR6qKnAdmt3jjWUOurok_CHkkuNk7wZIrDbDmus_Apt10iQgiodYZbDynoikF85luS_f3EeoN366WJYaa4f5tXeZCprtISgJ2R9CWMSsnUQOM3MutQmP9iNUZYSepSReubZ-67GR8MqXduQAd-mZqeQgy0d9OFT4fI2ahtpbuRLYIsz8sfuPLrxSse42CMNmaGG4UOvtiHVA-JgAf5MlwPQ",
									"type": "string"
								}
							]
						},
						"method": "PATCH",
						"header": [],
						"body": {
							"mode": "raw",
							"raw": "{\n\t\"name\": \"76ers\",\n\t\"home_state\": \"Philadelphia\"\n\t\n}",
							"options": {
								"raw": {
									"language": "json"
								}
							}
						},
						"url": {
							"raw": "https://udacity-nba-api.herokuapp.com/teams/9",
							"protocol": "https",
							"host": [
								"udacity-nba-api",
								"herokuapp",
								"com"
							],
							"path": [
								"teams",
								"9"
							]
						},
						"description": "update a team "
					},
					"response": []
				},
				{
					"name": "Updated Player",
					"event": [
						{
							"listen": "test",
							"script": {
								"exec": [
									"pm.test('Status code 200', function(){\r",
									"    pm.response.to.have.status(200)\r",
									"})"
								],
								"type": "text/javascript"
							}
						}
					],
					"request": {
						"auth": {
							"type": "bearer",
							"bearer": [
								{
									"key": "token",
									"value": "eyJhbGciOiJSUzI1NiIsInR5cCI6IkpXVCIsImtpZCI6Im5YcFc4ZWRMbmR6aFFQOUZjTXNyOSJ9.eyJpc3MiOiJodHRwczovL2F1dGgwLWZzbmQudXMuYXV0aDAuY29tLyIsInN1YiI6ImF1dGgwfDVmZmRkZTQ4MTMwOWUzMDA2OWM0MzRiNCIsImF1ZCI6Im5iYV9kYXRhX2FwaSIsImlhdCI6MTYxNDMxNjQ3MCwiZXhwIjoxNjE0MzIzNjcwLCJhenAiOiJmM0RLcWpxOEsySGhKZnI5dWJOU25ReFY2YVl4MjJaWiIsInNjb3BlIjoiIiwicGVybWlzc2lvbnMiOlsiZGVsZXRlOnBsYXllcnMiLCJwYXRjaDpwbGF5ZXJzIiwicGF0Y2g6dGVhbXMiLCJwb3N0OnBsYXllcnMiXX0.KA4eopbhlFtFLuK9G8NfKFuAQkE-rEeg21NyG0Jb3Ht1fKIzSltqPvyjLZKglhWf4i1woMMZI6EeqAijuMSYO6dnxa_UBRKmTEsPHOoFCNPPW-uaRqco1l0bHZKeNExQR6qKnAdmt3jjWUOurok_CHkkuNk7wZIrDbDmus_Apt10iQgiodYZbDynoikF85luS_f3EeoN366WJYaa4f5tXeZCprtISgJ2R9CWMSsnUQOM3MutQmP9iNUZYSepSReubZ-67GR8MqXduQAd-mZqeQgy0d9OFT4fI2ahtpbuRLYIsz8sfuPLrxSse42CMNmaGG4UOvtiHVA-JgAf5MlwPQ",
									"type": "string"
								}
							]
						},
						"method": "PATCH",
						"header": [],
						"body": {
							"mode": "raw",
							"raw": "{\n\t\"first_name\": \"Joel\"\n}",
							"options": {
								"raw": {
									"language": "json"
								}
							}
						},
						"url": {
							"raw": "https://udacity-nba-api.herokuapp.com/players/12",
							"protocol": "https",
							"host": [
								"udacity-nba-api",
								"herokuapp",
								"com"
							],
							"path": [
								"players",
								"12"
							]
						},
						"description": "patch player information"
					},
					"response": []
				},
				{
					"name": "Delete Player",
					"event": [
						{
							"listen": "test",
							"script": {
								"exec": [
									"pm.test('Status code 200', function(){\r",
									"    pm.response.to.have.status(200)\r",
									"})"
								],
								"type": "text/javascript"
							}
						}
					],
					"request": {
						"auth": {
							"type": "bearer",
							"bearer": [
								{
									"key": "token",
									"value": "eyJhbGciOiJSUzI1NiIsInR5cCI6IkpXVCIsImtpZCI6Im5YcFc4ZWRMbmR6aFFQOUZjTXNyOSJ9.eyJpc3MiOiJodHRwczovL2F1dGgwLWZzbmQudXMuYXV0aDAuY29tLyIsInN1YiI6ImF1dGgwfDVmZmRkZTQ4MTMwOWUzMDA2OWM0MzRiNCIsImF1ZCI6Im5iYV9kYXRhX2FwaSIsImlhdCI6MTYxNDMxNjQ3MCwiZXhwIjoxNjE0MzIzNjcwLCJhenAiOiJmM0RLcWpxOEsySGhKZnI5dWJOU25ReFY2YVl4MjJaWiIsInNjb3BlIjoiIiwicGVybWlzc2lvbnMiOlsiZGVsZXRlOnBsYXllcnMiLCJwYXRjaDpwbGF5ZXJzIiwicGF0Y2g6dGVhbXMiLCJwb3N0OnBsYXllcnMiXX0.KA4eopbhlFtFLuK9G8NfKFuAQkE-rEeg21NyG0Jb3Ht1fKIzSltqPvyjLZKglhWf4i1woMMZI6EeqAijuMSYO6dnxa_UBRKmTEsPHOoFCNPPW-uaRqco1l0bHZKeNExQR6qKnAdmt3jjWUOurok_CHkkuNk7wZIrDbDmus_Apt10iQgiodYZbDynoikF85luS_f3EeoN366WJYaa4f5tXeZCprtISgJ2R9CWMSsnUQOM3MutQmP9iNUZYSepSReubZ-67GR8MqXduQAd-mZqeQgy0d9OFT4fI2ahtpbuRLYIsz8sfuPLrxSse42CMNmaGG4UOvtiHVA-JgAf5MlwPQ",
									"type": "string"
								}
							]
						},
						"method": "DELETE",
						"header": [],
						"body": {
							"mode": "raw",
							"raw": "",
							"options": {
								"raw": {
									"language": "json"
								}
							}
						},
						"url": {
							"raw": "https://udacity-nba-api.herokuapp.com/players/18",
							"protocol": "https",
							"host": [
								"udacity-nba-api",
								"herokuapp",
								"com"
							],
							"path": [
								"players",
								"18"
							]
						},
						"description": "delete a player from team "
					},
					"response": []
				}
			],
			"auth": {
				"type": "bearer",
				"bearer": [
					{
						"key": "token",
						"value": "eyJhbGciOiJSUzI1NiIsInR5cCI6IkpXVCIsImtpZCI6Im5YcFc4ZWRMbmR6aFFQOUZjTXNyOSJ9.eyJpc3MiOiJodHRwczovL2F1dGgwLWZzbmQudXMuYXV0aDAuY29tLyIsInN1YiI6ImF1dGgwfDVmZmRkZTQ4MTMwOWUzMDA2OWM0MzRiNCIsImF1ZCI6Im5iYV9kYXRhX2FwaSIsImlhdCI6MTYxNTA1OTA2NSwiZXhwIjoxNjE1MDY2MjY1LCJhenAiOiJmM0RLcWpxOEsySGhKZnI5dWJOU25ReFY2YVl4MjJaWiIsInNjb3BlIjoiIiwicGVybWlzc2lvbnMiOlsiZGVsZXRlOnBsYXllcnMiLCJwYXRjaDpwbGF5ZXJzIiwicGF0Y2g6dGVhbXMiLCJwb3N0OnBsYXllcnMiXX0.3CqsWnqn0l5fCV_HkfRLa3lWgoo5-jKUKZhXEuTaPG7OovbSU3Vg2HmQ1BxePkqXj1GV0Wwy0MDOVUINS9p03uLSSXmDhpezJtN8P7j00CgEbMwp6gWBSB2JIjldZDERllmOaqzdy-YfdNDoja2CBSLlkFZBy-5-hww2f21pCI8HF9yCnB-AyFzHb8lNqisB7qiwm1Tn26Gda32c55L3O1NiIEan2S4q04lxLNRlZob0X0LHI21oH-ue_H3NaKBZocQXrsWOxiSCMtAuWAhg3416H79jt6db3nT1TTAzucTYbfJv42FIxLCqspNV7YoVNbciJ_gEU1t3Yl78FCNwPw\n\n",
						"type": "string"
					}
				]
			},
			"event": [
				{
					"listen": "prerequest",
					"script": {
						"type": "text/javascript",
						"exec": [
							""
						]
					}
				},
				{
					"listen": "test",
					"script": {
						"type": "text/javascript",
						"exec": [
							""
						]
					}
				}
			]
		},
		{
			"name": "Venue Management",
			"item": [
				{
					"name": "Post Venue",
					"event": [
						{
							"listen": "test",
							"script": {
								"exec": [
									"pm.test(\"response status code 200\", function (){\r",
									"    pm.response.to.have.status(200)\r",
									"})"
								],
								"type": "text/javascript"
							}
						}
					],
					"request": {
						"method": "POST",
						"header": [],
						"body": {
							"mode": "raw",
							"raw": "{\n\t\"name\": \"AmericanAirlines Arena\",\n\t\"address\": \"2121 Biscayne Blvd, Miami\",\n\t\"city\": \"florida\",\n\t\"zipcode\": \"33137\",\n\t\"is_available\": false,\n\t\"image\": \"https://www.aaarena.com/assets/img/Arena-Night-Interior-Slide-be90c5bf85.jpg\",\n\t\"description\": \"At AmericanAirlines Arena, it is our mission to deliver exceptional guest service, by surpassing each guest’s highest level of expectation.\"\n}",
							"options": {
								"raw": {
									"language": "json"
								}
							}
						},
						"url": {
							"raw": "https://udacity-nba-api.herokuapp.com/venues",
							"protocol": "https",
							"host": [
								"udacity-nba-api",
								"herokuapp",
								"com"
							],
							"path": [
								"venues"
							]
						}
					},
					"response": []
				},
				{
					"name": "Updated Venue",
					"event": [
						{
							"listen": "test",
							"script": {
								"exec": [
									"pm.test(\"response status code 200\", function (){\r",
									"    pm.response.to.have.status(200)\r",
									"})"
								],
								"type": "text/javascript"
							}
						}
					],
					"request": {
						"method": "PATCH",
						"header": [],
						"body": {
							"mode": "raw",
							"raw": "{\n\t\"name\": \"America Arena\"\n}",
							"options": {
								"raw": {
									"language": "json"
								}
							}
						},
						"url": {
							"raw": "https://udacity-nba-api.herokuapp.com/venues/1",
							"protocol": "https",
							"host": [
								"udacity-nba-api",
								"herokuapp",
								"com"
							],
							"path": [
								"venues",
								"1"
							]
						},
						"description": "update a event"
					},
					"response": []
				},
				{
					"name": "Delete Venue",
					"event": [
						{
							"listen": "test",
							"script": {
								"exec": [
									"pm.test(\"Status code is 200\", function () {",
									"    pm.response.to.have.status(200);",
									"});",
									""
								],
								"type": "text/javascript"
							}
						}
					],
					"request": {
						"method": "DELETE",
						"header": [],
						"url": {
							"raw": "https://udacity-nba-api.herokuapp.com/venues/7",
							"protocol": "https",
							"host": [
								"udacity-nba-api",
								"herokuapp",
								"com"
							],
							"path": [
								"venues",
								"7"
							]
						},
						"description": "delete venue"
					},
					"response": []
				},
				{
					"name": "Post Event",
					"event": [
						{
							"listen": "test",
							"script": {
								"exec": [
									"pm.test(\"response status code 200\", function (){\r",
									"    pm.response.to.have.status(200)\r",
									"})"
								],
								"type": "text/javascript"
							}
						}
					],
					"request": {
						"method": "POST",
						"header": [],
						"body": {
							"mode": "raw",
							"raw": "{\n    \"team_id\": 23,\n    \"team_id_two\": 26,\n    \"venue_id\":  2,\n    \"start_time\": \"2021-12-18 20:00:00\"\n}",
							"options": {
								"raw": {
									"language": "json"
								}
							}
						},
						"url": {
							"raw": "https://udacity-nba-api.herokuapp.com/events",
							"protocol": "https",
							"host": [
								"udacity-nba-api",
								"herokuapp",
								"com"
							],
							"path": [
								"events"
							]
						}
					},
					"response": []
				},
				{
					"name": "Updated Event",
					"event": [
						{
							"listen": "test",
							"script": {
								"exec": [
									"pm.test(\"response status code 200\", function (){\r",
									"    pm.response.to.have.status(200)\r",
									"})"
								],
								"type": "text/javascript"
							}
						}
					],
					"request": {
						"method": "PATCH",
						"header": [],
						"body": {
							"mode": "raw",
							"raw": "{\n    \"team_id\": 16\n}",
							"options": {
								"raw": {
									"language": "json"
								}
							}
						},
						"url": {
							"raw": "https://udacity-nba-api.herokuapp.com/events/17",
							"protocol": "https",
							"host": [
								"udacity-nba-api",
								"herokuapp",
								"com"
							],
							"path": [
								"events",
								"17"
							]
						},
						"description": "updates events "
					},
					"response": []
				},
				{
					"name": "Delete Event",
					"event": [
						{
							"listen": "test",
							"script": {
								"exec": [
									"pm.test(\"response status code 200\", function (){\r",
									"    pm.response.to.have.status(200)\r",
									"})"
								],
								"type": "text/javascript"
							}
						}
					],
					"request": {
						"method": "DELETE",
						"header": [],
						"body": {
							"mode": "raw",
							"raw": "{\n    \"team_id\": 5\n}",
							"options": {
								"raw": {
									"language": "json"
								}
							}
						},
						"url": {
							"raw": "https://udacity-nba-api.herokuapp.com/events/18",
							"protocol": "https",
							"host": [
								"udacity-nba-api",
								"herokuapp",
								"com"
							],
							"path": [
								"events",
								"18"
							]
						}
					},
					"response": []
				},
				{
					"name": "Post Team",
					"event": [
						{
							"listen": "test",
							"script": {
								"exec": [
									"pm.test('Status code 401', function(){\r",
									"    pm.response.to.have.status(401)\r",
									"})\r",
									"\r",
									""
								],
								"type": "text/javascript"
							}
						}
					],
					"request": {
						"method": "POST",
						"header": [],
						"body": {
							"mode": "raw",
							"raw": "{\r\n\t\"name\": \"test\",\r\n\t\"home_state\": \"new jersey \",\r\n\t\"losses\": 5,\r\n\t\"wins\": 12,\r\n\t\"logo\": \"https://upload.wikimedia.org/wikipedia/en/thumb/5/5d/Oklahoma_City_Thunder.svg/1200px-Oklahoma_City_Thunder.svg.png\"\r\n\t\r\n}",
							"options": {
								"raw": {
									"language": "json"
								}
							}
						},
						"url": {
							"raw": "https://udacity-nba-api.herokuapp.com/teams",
							"protocol": "https",
							"host": [
								"udacity-nba-api",
								"herokuapp",
								"com"
							],
							"path": [
								"teams"
							]
						},
						"description": "post a player \r\n"
					},
					"response": []
				},
				{
					"name": "Updated Team",
					"event": [
						{
							"listen": "test",
							"script": {
								"exec": [
									"pm.test('Status code 401', function(){\r",
									"    pm.response.to.have.status(401)\r",
									"})\r",
									"\r",
									""
								],
								"type": "text/javascript"
							}
						}
					],
					"request": {
						"method": "PATCH",
						"header": [],
						"body": {
							"mode": "raw",
							"raw": "{\r\n    \"name\": \"Knicks\"\r\n}",
							"options": {
								"raw": {
									"language": "json"
								}
							}
						},
						"url": {
							"raw": "https://udacity-nba-api.herokuapp.com/teams/1",
							"protocol": "https",
							"host": [
								"udacity-nba-api",
								"herokuapp",
								"com"
							],
							"path": [
								"teams",
								"1"
							]
						},
						"description": "post a team "
					},
					"response": []
				},
				{
					"name": "Delete Team",
					"event": [
						{
							"listen": "test",
							"script": {
								"exec": [
									"pm.test('Status code 401', function(){\r",
									"    pm.response.to.have.status(401)\r",
									"})\r",
									"\r",
									""
								],
								"type": "text/javascript"
							}
						}
					],
					"request": {
						"method": "DELETE",
						"header": [],
						"body": {
							"mode": "raw",
							"raw": "",
							"options": {
								"raw": {
									"language": "json"
								}
							}
						},
						"url": {
							"raw": "https://udacity-nba-api.herokuapp.com/teams",
							"protocol": "https",
							"host": [
								"udacity-nba-api",
								"herokuapp",
								"com"
							],
							"path": [
								"teams"
							]
						}
					},
					"response": []
				},
				{
					"name": "Post a Player",
					"event": [
						{
							"listen": "test",
							"script": {
								"exec": [
									"pm.test('Status code 401', function(){\r",
									"    pm.response.to.have.status(401)\r",
									"})"
								],
								"type": "text/javascript"
							}
						}
					],
					"request": {
						"method": "POST",
						"header": [],
						"body": {
							"mode": "raw",
							"raw": "{\n\t\"first_name\": \"Derrick\",\n\t\"last_name\": \"Rose\",\n    \"player_number\": 4,\n\t\"team\": \"Knicks\",\n\t\"mpg\": 24.6,\n\t\"ppg\": 12.5,\n\t\"rpg\": 2.6,\n\t\"apg\": 4.9,\n\t\"team_id\": 1\n}",
							"options": {
								"raw": {
									"language": "json"
								}
							}
						},
						"url": {
							"raw": "https://udacity-nba-api.herokuapp.com/players",
							"protocol": "https",
							"host": [
								"udacity-nba-api",
								"herokuapp",
								"com"
							],
							"path": [
								"players"
							]
						}
					},
					"response": []
				},
				{
					"name": "Updated a player",
					"event": [
						{
							"listen": "test",
							"script": {
								"exec": [
									"pm.test('Status code 401', function(){\r",
									"    pm.response.to.have.status(401)\r",
									"})"
								],
								"type": "text/javascript"
							}
						}
					],
					"request": {
						"method": "PATCH",
						"header": [],
						"body": {
							"mode": "raw",
							"raw": "{\n\t\"first_name\": \"Joels\"\n\n}",
							"options": {
								"raw": {
									"language": "json"
								}
							}
						},
						"url": {
							"raw": "https://udacity-nba-api.herokuapp.com/players/12",
							"protocol": "https",
							"host": [
								"udacity-nba-api",
								"herokuapp",
								"com"
							],
							"path": [
								"players",
								"12"
							]
						}
					},
					"response": []
				},
				{
					"name": "Delete Player",
					"event": [
						{
							"listen": "test",
							"script": {
								"exec": [
									"pm.test('Status code 401', function(){\r",
									"    pm.response.to.have.status(401)\r",
									"})"
								],
								"type": "text/javascript"
							}
						}
					],
					"request": {
						"method": "DELETE",
						"header": [],
						"body": {
							"mode": "raw",
							"raw": "",
							"options": {
								"raw": {
									"language": "json"
								}
							}
						},
						"url": {
							"raw": "https://udacity-nba-api.herokuapp.com/players/5",
							"protocol": "https",
							"host": [
								"udacity-nba-api",
								"herokuapp",
								"com"
							],
							"path": [
								"players",
								"5"
							]
						},
						"description": "delete player\r\n"
					},
					"response": []
				}
			],
			"description": "owner or managment of venues ",
			"auth": {
				"type": "bearer",
				"bearer": [
					{
						"key": "token",
						"value": "eyJhbGciOiJSUzI1NiIsInR5cCI6IkpXVCIsImtpZCI6Im5YcFc4ZWRMbmR6aFFQOUZjTXNyOSJ9.eyJpc3MiOiJodHRwczovL2F1dGgwLWZzbmQudXMuYXV0aDAuY29tLyIsInN1YiI6ImF1dGgwfDYwMzQyZGZmMDdjM2NkMDA2ODUwOTI0NiIsImF1ZCI6Im5iYV9kYXRhX2FwaSIsImlhdCI6MTYxNTA1OTEyOCwiZXhwIjoxNjE1MDY2MzI4LCJhenAiOiJmM0RLcWpxOEsySGhKZnI5dWJOU25ReFY2YVl4MjJaWiIsInNjb3BlIjoiIiwicGVybWlzc2lvbnMiOlsiZGVsZXRlOmV2ZW50cyIsImRlbGV0ZTp2ZW51ZXMiLCJwYXRjaDpldmVudHMiLCJwYXRjaDp2ZW51ZXMiLCJwb3N0OmV2ZW50cyIsInBvc3Q6dmVudWVzIl19.3bOKi0u4BWnrBePHaE01eE1UWnblVJdK9DyfgtFEthD3i5tuEUb2xIx__vVbZufNyFz499rcoZEfo5xYLOwVnNT-K4UfyiNHkxH_eA__tyC9kgD33L5xCEVaxHouNpUx5WTLkHsfEXTL-qC_n0W1SDYJ1nobLzsaFc4IEu_gjIw3zo6gnei_1yd1nhVo5Hh63UyDlsI5Ko-q6VLZrfjWDyyAM2ZW2NGw4-ztCLymeQXlz-ARFhRdDky57MDFKNLOhfRkhr8qX6yZvQ1ojbAZlqpIckxhAOoyf7071J5GcpD35i-u6c4TjpdhRk53WI7A-4SrXblKaFM2k7Aze3NgXg",
						"type": "string"
					}
				]
			},
			"event": [
				{
					"listen": "prerequest",
					"script": {
						"type": "text/javascript",
						"exec": [
							""
						]
					}
				},
				{
					"listen": "test",
					"script": {
						"type": "text/javascript",
						"exec": [
							""
						]
					}
				}
			]
		},
		{
			"name": "Nba Commision",
			"item": [
				{
					"name": "Post Team",
					"event": [
						{
							"listen": "test",
							"script": {
								"exec": [
									"pm.test('Status code 200', function(){\r",
									"    pm.response.to.have.status(200)\r",
									"})\r",
									"\r",
									""
								],
								"type": "text/javascript"
							}
						}
					],
					"request": {
						"method": "POST",
						"header": [],
						"body": {
							"mode": "raw",
							"raw": "{\r\n  \t\"name\": \"test_team\",\r\n\t\"home_state\": \"bronx\",\r\n\t\"losses\": 5,\r\n\t\"wins\": 12,\r\n\t\"logo\": \"https://upload.wikimedia.org/wikipedia/en/thumb/5/5d/Oklahoma_City_Thunder.svg/1200px-Oklahoma_City_Thunder.svg.png\"\r\n\t\r\n}",
							"options": {
								"raw": {
									"language": "json"
								}
							}
						},
						"url": {
							"raw": "https://udacity-nba-api.herokuapp.com/teams",
							"protocol": "https",
							"host": [
								"udacity-nba-api",
								"herokuapp",
								"com"
							],
							"path": [
								"teams"
							]
						},
						"description": "try to post a team from unauthorize account"
					},
					"response": []
				},
				{
					"name": "Updated Team",
					"event": [
						{
							"listen": "test",
							"script": {
								"exec": [
									"pm.test('Status code 200', function(){\r",
									"    pm.response.to.have.status(200)\r",
									"})\r",
									"\r",
									""
								],
								"type": "text/javascript"
							}
						}
					],
					"request": {
						"method": "PATCH",
						"header": [],
						"body": {
							"mode": "raw",
							"raw": "{\r\n    \"name\": \"bronx destroyers\"\r\n}",
							"options": {
								"raw": {
									"language": "json"
								}
							}
						},
						"url": {
							"raw": "https://udacity-nba-api.herokuapp.com/teams/46",
							"protocol": "https",
							"host": [
								"udacity-nba-api",
								"herokuapp",
								"com"
							],
							"path": [
								"teams",
								"46"
							]
						},
						"description": "update team "
					},
					"response": []
				},
				{
					"name": "Delete Team",
					"event": [
						{
							"listen": "test",
							"script": {
								"exec": [
									"pm.test('Status code 200', function(){\r",
									"    pm.response.to.have.status(200)\r",
									"})\r",
									"\r",
									""
								],
								"type": "text/javascript"
							}
						}
					],
					"request": {
						"method": "DELETE",
						"header": [],
						"body": {
							"mode": "raw",
							"raw": "",
							"options": {
								"raw": {
									"language": "json"
								}
							}
						},
						"url": {
							"raw": "https://udacity-nba-api.herokuapp.com/teams/45",
							"protocol": "https",
							"host": [
								"udacity-nba-api",
								"herokuapp",
								"com"
							],
							"path": [
								"teams",
								"45"
							]
						},
						"description": "delete a team "
					},
					"response": []
				},
				{
					"name": "Post a Player",
					"event": [
						{
							"listen": "test",
							"script": {
								"exec": [
									"pm.test('Status code 200', function(){\r",
									"    pm.response.to.have.status(200)\r",
									"})"
								],
								"type": "text/javascript"
							}
						}
					],
					"request": {
						"method": "POST",
						"header": [],
						"body": {
							"mode": "raw",
							"raw": "{\n\t\"first_name\": \"LaMelo\",\n\t\"last_name\": \"Ball\",\n    \"player_number\": 2,\n\t\"team\": \"Hornets\",\n\t\"mpg\": 24.6,\n\t\"ppg\": 12.5,\n\t\"rpg\": 2.6,\n\t\"apg\": 4.9,\n\t\"team_id\": 11\n}",
							"options": {
								"raw": {
									"language": "json"
								}
							}
						},
						"url": {
							"raw": "https://udacity-nba-api.herokuapp.com/players",
							"protocol": "https",
							"host": [
								"udacity-nba-api",
								"herokuapp",
								"com"
							],
							"path": [
								"players"
							]
						}
					},
					"response": []
				},
				{
					"name": "Updated a player",
					"event": [
						{
							"listen": "test",
							"script": {
								"exec": [
									"pm.test('Status code 200', function(){\r",
									"    pm.response.to.have.status(200)\r",
									"})"
								],
								"type": "text/javascript"
							}
						}
					],
					"request": {
						"method": "PATCH",
						"header": [],
						"body": {
							"mode": "raw",
							"raw": "{\n\t\"apg\": 8.5\n}",
							"options": {
								"raw": {
									"language": "json"
								}
							}
						},
						"url": {
							"raw": "https://udacity-nba-api.herokuapp.com/players/12",
							"protocol": "https",
							"host": [
								"udacity-nba-api",
								"herokuapp",
								"com"
							],
							"path": [
								"players",
								"12"
							]
						},
						"description": "update players "
					},
					"response": []
				},
				{
					"name": "Delete Player",
					"event": [
						{
							"listen": "test",
							"script": {
								"exec": [
									"pm.test('Status code 401', function(){\r",
									"    pm.response.to.have.status(401)\r",
									"})"
								],
								"type": "text/javascript"
							}
						}
					],
					"request": {
						"method": "DELETE",
						"header": [],
						"body": {
							"mode": "raw",
							"raw": "",
							"options": {
								"raw": {
									"language": "json"
								}
							}
						},
						"url": {
							"raw": "https://udacity-nba-api.herokuapp.com/players/15",
							"protocol": "https",
							"host": [
								"udacity-nba-api",
								"herokuapp",
								"com"
							],
							"path": [
								"players",
								"15"
							]
						}
					},
					"response": []
				}
			],
			"description": "in charge of decision for the nba ",
			"auth": {
				"type": "bearer",
				"bearer": [
					{
						"key": "token",
						"value": "eyJhbGciOiJSUzI1NiIsInR5cCI6IkpXVCIsImtpZCI6Im5YcFc4ZWRMbmR6aFFQOUZjTXNyOSJ9.eyJpc3MiOiJodHRwczovL2F1dGgwLWZzbmQudXMuYXV0aDAuY29tLyIsInN1YiI6ImF1dGgwfDYwMDQ4NDMyYmY1NzUwMDA3MDM0OWI0YiIsImF1ZCI6Im5iYV9kYXRhX2FwaSIsImlhdCI6MTYxNTA1OTE5MCwiZXhwIjoxNjE1MDY2MzkwLCJhenAiOiJmM0RLcWpxOEsySGhKZnI5dWJOU25ReFY2YVl4MjJaWiIsInNjb3BlIjoiIiwicGVybWlzc2lvbnMiOlsiZGVsZXRlOmV2ZW50cyIsImRlbGV0ZTpwbGF5ZXJzIiwiZGVsZXRlOnRlYW1zIiwicGF0Y2g6cGxheWVycyIsInBhdGNoOnRlYW1zIiwicG9zdDpwbGF5ZXJzIiwicG9zdDp0ZWFtcyJdfQ.qwl-Dk0x-EcfzZjgwpTGz8uqgQioCUnlm0e4peORbEiYTRfBwdrh_Zi1ovi7us7Q3le_oBWIvULvSy5QLM_2EJgI3K3m_dRcis8WRmZs6f7jbxyb4xAnKCChWDInvzgvn6HhY5EQgyvTuGEPJTCV-B5DRCHe_WIoC5d2tjaL7VmipL3Xm-EEMYw5GRAEOWsc7c4a0pggibQWZnwnkztc3RTmQVA4dVt7-U16aISBjLIROiDa_ThoOQ2c5Mx05w60pII0cKqZ0O9pexdIlOxhT4K48MO3zUcGigu6XNlqjfM_35YRxAUkPn4jJ_H7BYNgZJG6Sy5ADgH27WG1mMP_vQ",
						"type": "string"
					}
				]
			},
			"event": [
				{
					"listen": "prerequest",
					"script": {
						"type": "text/javascript",
						"exec": [
							""
						]
					}
				},
				{
					"listen": "test",
					"script": {
						"type": "text/javascript",
						"exec": [
							""
						]
					}
				}
			]
		}
	]
}